LICENSE
MANIFEST.in
README.md
setup.py
batesterwithcustomparamdemov1/__init__.py
batesterwithcustomparamdemov1/api_helper.py
batesterwithcustomparamdemov1/batesterwithcustomparamdemov_1_client.py
batesterwithcustomparamdemov1/configuration.py
batesterwithcustomparamdemov1/decorators.py
batesterwithcustomparamdemov1.egg-info/PKG-INFO
batesterwithcustomparamdemov1.egg-info/SOURCES.txt
batesterwithcustomparamdemov1.egg-info/dependency_links.txt
batesterwithcustomparamdemov1.egg-info/requires.txt
batesterwithcustomparamdemov1.egg-info/top_level.txt
batesterwithcustomparamdemov1/controllers/__init__.py
batesterwithcustomparamdemov1/controllers/api_controller.py
batesterwithcustomparamdemov1/controllers/base_controller.py
batesterwithcustomparamdemov1/exceptions/__init__.py
batesterwithcustomparamdemov1/exceptions/api_exception.py
batesterwithcustomparamdemov1/http/__init__.py
batesterwithcustomparamdemov1/http/http_call_back.py
batesterwithcustomparamdemov1/http/http_client.py
batesterwithcustomparamdemov1/http/http_context.py
batesterwithcustomparamdemov1/http/http_method_enum.py
batesterwithcustomparamdemov1/http/http_request.py
batesterwithcustomparamdemov1/http/http_response.py
batesterwithcustomparamdemov1/http/requests_client.py
batesterwithcustomparamdemov1/http/auth/__init__.py
batesterwithcustomparamdemov1/http/auth/basic_auth.py
batesterwithcustomparamdemov1/models/__init__.py
batesterwithcustomparamdemov1/models/suite_code_enum.py
tests/__init__.py
tests/http_response_catcher.py
tests/test_helper.py
tests/controllers/__init__.py
tests/controllers/controller_test_base.py
tests/controllers/test_api_controller.py