Metadata-Version: 1.0
Name: batesterwithcustomparamdemov1
Version: 1.2.888
Summary: TODO: add library description
Home-page: https://apimatic.io
Author: APIMatic SDK Generator
Author-email: support@apimatic.io
License: UNKNOWN
Platform: UNKNOWN
